{
    "newt_affects": ["C4", "C5", "C7", "C8", "C9", "C10", "C11", "C12", "C14", "C15", "C17", "C18", "C20", "C21", "C23", "C24", "C25", "C27", "C29", "C30", "C33", "C36", "C39"],  
    "salamander_affects": ["U10", "U11", "U12", "U15", "U18", "U20", "U24", "U25", "U27", "U29", "U30", "U31", "U32", "U33", "U36", "U38"],
    "lizard_king_affects": ["R6", "R10", "R18", "R21", "R23", "R25", "R29", "R30", "R31", "R36", "R38", "R39", "R42", "R44", "R49", "R50", "R56", "R59", "R63"],
    "leviathan_affects": ["E14", "E15", "E17", "E18", "E20", "E21", "E24", "E26", "E27", "E29", "E33", "E34", "E39", "E42", "E45"],
    "python_affects": ["C9", "C12", "C15", "C21", "C30", "C33", "C36", "U12", "U15", "U18", "U32", "U33", "U36", "U38", "R6", "R18", "R31", "R36", "R39", "E18", "E33"],
    "king_cobra_affects": ["C8", "C9", "C12", "C14", "C15", "C20", "C21", "C24", "C27", "C30", "C33", "C36", "C39", "U12", "U15", "U18", "U27", "U29", "U30", "U32", "U33", "U36", "U38", 
    "R6", "R18", "R21", "R31", "R36", "R38", "R39", "R42", "R49", "R56", "R63", "E14", "E17", "E18", "E20", "E27", "E29", "E33", "E39", "E42", "E45", "L5", "L17", "L26", "L27", "L47"],
    "sea_serpent_affects": ["python", "king_cobra"],
    "tiamat_affects": ["sea_serpent"],
    "crocodile_affects": ["C35", "U8", "U9", "U21", "R8", "R9", "R45", "R54", "R61", "E5", "E6", "E9", "E10", "E22", "E26", "E30", "E35", "L4", "L6", "L7", "L8", "L29", "L47"],
    "fortune_ignored_shards": ["C19", "U4", "U16", "U21", "U28", "R27", "R45", "R53", "R61", "R64", "L4", "L9", "L48", "L51"]
}